popoto/__init__.py
popoto_api/__init__.py
popoto_api/popoto.py
popoto_data_server/__init__.py
popoto_data_server/pds.py
popoto_api-0.5.1.dist-info/METADATA
popoto_api-0.5.1.dist-info/WHEEL
popoto_api-0.5.1.dist-info/entry_points.txt
popoto_api-0.5.1.dist-info/RECORD
