Metadata-Version: 2.4
Name: popoto-api
Version: 0.5.1
Summary: Package containing the Popoto Modem Python API.
Author-email: Aaron Bangs <aaron@delresearch.com>, Edgar Bangs <edgar@delresearch.com>, "James A. DellaMorte" <jamesanthony@popotomodem.com>, Jim DellaMorte <jim@delresearch.com>, Joseph DellaMorte <joseph@delresearch.com>, John DellaMorte <john@delresearch.com>
Classifier: Operating System :: OS Independent
Classifier: Programming Language :: Python :: 3
Classifier: Programming Language :: Python :: 3.8
Classifier: Programming Language :: Python :: 3.9
Classifier: Programming Language :: Python :: 3.10
Classifier: Programming Language :: Python :: 3.11
Classifier: Programming Language :: Python :: 3.12
Classifier: Programming Language :: Python :: 3.13
Requires-Python: >=3.9
Provides-Extra: all
Requires-Dist: numpy; extra == 'all'
Requires-Dist: progressbar; extra == 'all'
Requires-Dist: scipy; extra == 'all'
Provides-Extra: test
Requires-Dist: pytest; extra == 'test'
